yf_simple_fetcher/__init__.py
yf_simple_fetcher/fetcher.py
yf_simple_fetcher-0.1.2.dist-info/licenses/LICENSE
yf_simple_fetcher-0.1.2.dist-info/METADATA
yf_simple_fetcher-0.1.2.dist-info/WHEEL
yf_simple_fetcher-0.1.2.dist-info/top_level.txt
yf_simple_fetcher-0.1.2.dist-info/RECORD
