Metadata-Version: 2.4
Name: yf_simple_fetcher
Version: 0.1.2
Summary: A simple package to fetch ready-to-use stock data from yfinance
Author-email: Mpho <mphosomo07@gmail.com>
License-Expression: MIT
Project-URL: Homepage, https://github.com/devwithmpho/yf_simple_fetcher
Project-URL: Issues, https://github.com/devwithmpho/yf_simple_fetcher/issues
Classifier: Programming Language :: Python :: 3
Classifier: Operating System :: OS Independent
Requires-Python: >=3.9
License-File: LICENSE
Dynamic: license-file
